motd/__init__.py
motd/motd.py
motd-0.3.0.dist-info/METADATA
motd-0.3.0.dist-info/WHEEL
motd-0.3.0.dist-info/top_level.txt
motd-0.3.0.dist-info/RECORD
