Metadata-Version: 2.1
Name: motd
Version: 0.3.0
Summary: Non-official Mathematicians Of The Day output from website
Home-page: https://twitter.com/david_cobac
Author: David COBAC
Author-email: david.cobac@gmail.com
License: CC-BY-NC-SA
Keywords: motd,date,math,history
Platform: UNKNOWN
Classifier: Programming Language :: Python :: 3
